README.md
setup.py
alibabacloud_tea_xml/__init__.py
alibabacloud_tea_xml/client.py
alibabacloud_tea_xml_py2.egg-info/PKG-INFO
alibabacloud_tea_xml_py2.egg-info/SOURCES.txt
alibabacloud_tea_xml_py2.egg-info/dependency_links.txt
alibabacloud_tea_xml_py2.egg-info/requires.txt
alibabacloud_tea_xml_py2.egg-info/top_level.txt